Workbook

Sheet Definition of Terms
A1: Term | B1: Definition
A2: KAILA | B2: The proposed local services marketplace that helps clients find trusted local help and helps skilled workers become more visible.
A3: Client | B3: A person, household, business, or organization that posts a service need or hires a provider through KAILA.
A4: Provider | B4: A skilled worker, freelancer, technician, shop, or service professional who offers work through KAILA.
A5: Service Request | B5: A client post describing the job needed, location, budget, urgency, details, and optional photos or files.
A6: Offer | B6: A provider's response to a service request, including price, availability, scope notes, or proposed schedule.
A7: Counter-Offer | B7: A revised offer made when the provider or client proposes a different price, schedule, or service scope.
A8: Marketplace | B8: The two-sided system where clients and providers discover, evaluate, transact, and rate each other.
A9: MVP | B9: Minimum Viable Product; the simplest usable version of KAILA needed to test marketplace behavior.
A10: Pilot | B10: A limited real-world launch in one city or area used to validate demand, provider response, operations, and trust.
A11: Concierge Pilot | B11: A marketplace test using the existing browser MVP/native wrapper plus Facebook page posts, Messenger follow-up, and manual operations support.
A12: Verification | B12: The process of checking provider identity, service information, work samples, permits, certificates, or references.
... A18: Go/No-Go Criteria | B18: The evidence-based thresholds used to decide whether to proceed, narrow the scope, redesign, or pause.

Sheet Assumptions
A1: KAILA Financial Model - Assumptions
A2: Pilot City | B2: Base Case | C2: Source/Note
A3: Starting Active Providers | B3: 50 | C3: Internal assumption - target based on provider recruitment plan
A4: Starting Monthly Requests | B4: 30 | C4: Internal assumption - target based on validation plan
A5: Monthly Request Growth | B5: 0.12 | C5: Internal assumption - editable
A6: Completion Rate | B6: 0.5 | C6: Internal assumption - percentage of posted requests completed
A7: Average Job Value PHP | B7: 700 | C7: Internal assumption - blended average across small services
A8: Commission Rate | B8: 0 | C8: Phase 1 free; change after monetization
A9: Lead Credit Revenue per Provider PHP | B9: 0 | C9: Phase 1 free; optional later
A10: Premium Provider Fee PHP/mo | B10: 199 | C10: Optional premium visibility product
A11: Premium Provider Adoption | B11: 0 | C11: Phase 1 free; change in scenario
A12: Hosting/Tools PHP/mo | B12: 500 | C12: Lean pilot: free tiers/current hosting where possible
A13: Marketing PHP/mo | B13: 1000 | C13: Facebook page, organic posting, small boosts only when needed
A14: Operations Support PHP/mo | B14: 1000 | C14: Founder-led operations; small allowance for field support
... A17: Development Cost PHP/mo | B17: 0 | C17: Browser MVP and native wrapper already built; founder-led polish

Sheet Monthly Projection
A1: 36-Month Projection
A2: Metric | B2: Month 1 | C2: Month 2 | D2: Month 3 | E2: Month 4 | F2: Month 5 | G2: Month 6 | H2: Month 7 | I2: Month 8 | J2: Month 9 | K2: Month 10 | L2: Month 11 | M2: Month 12 | N2: Month 13 | O2: Month 14 | P2: Month 15 | Q2: Month 16 | R2: Month 17 | S2: Month 18 | T2: Month 19 | U2: Month 20 | V2: Month 21 | W2: Month 22 | X2: Month 23 | Y2: Month 24 | Z2: Month 25 | AA2: Month 26 | AB2: Month 27 | AC2: Month 28 | AD2: Month 29 | AE2: Month 30 | AF2: Month 31 | AG2: Month 32 | AH2: Month 33 | AI2: Month 34 | AJ2: Month 35 | AK2: Month 36
A3: Active Providers | B3: =ROUND('Assumptions'!B3,0) | C3: =ROUND(B3*1.05,0) | D3: =ROUND(C3*1.05,0) | E3: =ROUND(D3*1.05,0) | F3: =ROUND(E3*1.05,0) | G3: =ROUND(F3*1.05,0) | H3: =ROUND(G3*1.05,0) | I3: =ROUND(H3*1.05,0) | J3: =ROUND(I3*1.05,0) | ... AK3: =ROUND(AJ3*1.05,0)
A4: Posted Requests | B4: =ROUND('Assumptions'!B4,0) | C4: =ROUND(B4*(1+'Assumptions'!B5),0) | D4: =ROUND(C4*(1+'Assumptions'!B5),0) | E4: =ROUND(D4*(1+'Assumptions'!B5),0) | F4: =ROUND(E4*(1+'Assumptions'!B5),0) | G4: =ROUND(F4*(1+'Assumptions'!B5),0) | H4: =ROUND(G4*(1+'Assumptions'!B5),0) | I4: =ROUND(H4*(1+'Assumptions'!B5),0) | J4: =ROUND(I4*(1+'Assumptions'!B5),0) | K4: =ROUND(J4*(1+'Assumptions'!B5),0) | L4: =ROUND(K4*(1+'Assumptions'!B5),0) | M4: =ROUND(L4*(1+'Assumptions'!B5),0) | N4: =ROUND(M4*(1+'Assumptions'!B5),0) | O4: =ROUND(N4*(1+'Assumptions'!B5),0) | P4: =ROUND(O4*(1+'Assumptions'!B5),0) | Q4: =ROUND(P4*(1+'Assumptions'!B5),0) | R4: =ROUND(Q4*(1+'Assumptions'!B5),0) | S4: =ROUND(R4*(1+'Assumptions'!B5),0) | T4: =ROUND(S4*(1+'Assumptions'!B5),0) | U4: =ROUND(T4*(1+'Assumptions'!B5),0) | V4: =ROUND(U4*(1+'Assumptions'!B5),0) | W4: =ROUND(V4*(1+'Assumptions'!B5),0) | X4: =ROUND(W4*(1+'Assumptions'!B5),0) | Y4: =ROUND(X4*(1+'Assumptions'!B5),0) | Z4: =ROUND(Y4*(1+'Assumptions'!B5),0) | AA4: =ROUND(Z4*(1+'Assumptions'!B5),0) | AB4: =ROUND(AA4*(1+'Assumptions'!B5),0) | AC4: =ROUND(AB4*(1+'Assumptions'!B5),0) | AD4: =ROUND(AC4*(1+'Assumptions'!B5),0) | AE4: =ROUND(AD4*(1+'Assumptions'!B5),0) | AF4: =ROUND(AE4*(1+'Assumptions'!B5),0) | AG4: =ROUND(AF4*(1+'Assumptions'!B5),0) | AH4: =ROUND(AG4*(1+'Assumptions'!B5),0) | AI4: =ROUND(AH4*(1+'Assumptions'!B5),0) | AJ4: =ROUND(AI4*(1+'Assumptions'!B5),0) | AK4: =ROUND(AJ4*(1+'Assumptions'!B5),0)
A5: Completed Jobs | B5: =ROUND(B4*'Assumptions'!B6,0) | C5: =ROUND(C4*'Assumptions'!B6,0) | D5: =ROUND(D4*'Assumptions'!B6,0) | E5: =ROUND(E4*'Assumptions'!B6,0) | F5: =ROUND(F4*'Assumptions'!B6,0) | G5: =ROUND(G4*'Assumptions'!B6,0) | H5: =ROUND(H4*'Assumptions'!B6,0) | I5: =ROUND(I4*'Assumptions'!B6,0) | J5: =ROUND(J4*'Assumptions'!B6,0) | K5: =ROUND(K4*'Assumptions'!B6,0) | L5: =ROUND(L4*'Assumptions'!B6,0) | M5: =ROUND(M4*'Assumptions'!B6,0) | N5: =ROUND(N4*'Assumptions'!B6,0) | O5: =ROUND(O4*'Assumptions'!B6,0) | P5: =ROUND(P4*'Assumptions'!B6,0) | Q5: =ROUND(Q4*'Assumptions'!B6,0) | R5: =ROUND(R4*'Assumptions'!B6,0) | S5: =ROUND(S4*'Assumptions'!B6,0) | T5: =ROUND(T4*'Assumptions'!B6,0) | U5: =ROUND(U4*'Assumptions'!B6,0) | V5: =ROUND(V4*'Assumptions'!B6,0) | W5: =ROUND(W4*'Assumptions'!B6,0) | X5: =ROUND(X4*'Assumptions'!B6,0) | Y5: =ROUND(Y4*'Assumptions'!B6,0) | Z5: =ROUND(Z4*'Assumptions'!B6,0) | AA5: =ROUND(AA4*'Assumptions'!B6,0) | AB5: =ROUND(AB4*'Assumptions'!B6,0) | AC5: =ROUND(AC4*'Assumptions'!B6,0) | AD5: =ROUND(AD4*'Assumptions'!B6,0) | AE5: =ROUND(AE4*'Assumptions'!B6,0) | AF5: =ROUND(AF4*'Assumptions'!B6,0) | AG5: =ROUND(AG4*'Assumptions'!B6,0) | AH5: =ROUND(AH4*'Assumptions'!B6,0) | AI5: =ROUND(AI4*'Assumptions'!B6,0) | AJ5: =ROUND(AJ4*'Assumptions'!B6,0) | AK5: =ROUND(AK4*'Assumptions'!B6,0)
A6: GMV PHP | B6: =ROUND(B5*'Assumptions'!B7,0) | C6: =ROUND(C5*'Assumptions'!B7,0) | D6: =ROUND(D5*'Assumptions'!B7,0) | E6: =ROUND(E5*'Assumptions'!B7,0) | F6: =ROUND(F5*'Assumptions'!B7,0) | G6: =ROUND(G5*'Assumptions'!B7,0) | H6: =ROUND(H5*'Assumptions'!B7,0) | I6: =ROUND(I5*'Assumptions'!B7,0) | J6: =ROUND(J5*'Assumptions'!B7,0) | K6: =ROUND(K5*'Assumptions'!B7,0) | L6: =ROUND(L5*'Assumptions'!B7,0) | M6: =ROUND(M5*'Assumptions'!B7,0) | N6: =ROUND(N5*'Assumptions'!B7,0) | O6: =ROUND(O5*'Assumptions'!B7,0) | P6: =ROUND(P5*'Assumptions'!B7,0) | Q6: =ROUND(Q5*'Assumptions'!B7,0) | R6: =ROUND(R5*'Assumptions'!B7,0) | S6: =ROUND(S5*'Assumptions'!B7,0) | T6: =ROUND(T5*'Assumptions'!B7,0) | U6: =ROUND(U5*'Assumptions'!B7,0) | V6: =ROUND(V5*'Assumptions'!B7,0) | W6: =ROUND(W5*'Assumptions'!B7,0) | X6: =ROUND(X5*'Assumptions'!B7,0) | Y6: =ROUND(Y5*'Assumptions'!B7,0) | Z6: =ROUND(Z5*'Assumptions'!B7,0) | AA6: =ROUND(AA5*'Assumptions'!B7,0) | AB6: =ROUND(AB5*'Assumptions'!B7,0) | AC6: =ROUND(AC5*'Assumptions'!B7,0) | AD6: =ROUND(AD5*'Assumptions'!B7,0) | AE6: =ROUND(AE5*'Assumptions'!B7,0) | AF6: =ROUND(AF5*'Assumptions'!B7,0) | AG6: =ROUND(AG5*'Assumptions'!B7,0) | AH6: =ROUND(AH5*'Assumptions'!B7,0) | AI6: =ROUND(AI5*'Assumptions'!B7,0) | AJ6: =ROUND(AJ5*'Assumptions'!B7,0) | AK6: =ROUND(AK5*'Assumptions'!B7,0)
A7: Commission Revenue PHP | B7: =ROUND(B6*'Assumptions'!B8,0) | C7: =ROUND(C6*'Assumptions'!B8,0) | D7: =ROUND(D6*'Assumptions'!B8,0) | E7: =ROUND(E6*'Assumptions'!B8,0) | F7: =ROUND(F6*'Assumptions'!B8,0) | G7: =ROUND(G6*'Assumptions'!B8,0) | H7: =ROUND(H6*'Assumptions'!B8,0) | I7: =ROUND(I6*'Assumptions'!B8,0) | J7: =ROUND(J6*'Assumptions'!B8,0) | K7: =ROUND(K6*'Assumptions'!B8,0) | L7: =ROUND(L6*'Assumptions'!B8,0) | M7: =ROUND(M6*'Assumptions'!B8,0) | N7: =ROUND(N6*'Assumptions'!B8,0) | O7: =ROUND(O6*'Assumptions'!B8,0) | P7: =ROUND(P6*'Assumptions'!B8,0) | Q7: =ROUND(Q6*'Assumptions'!B8,0) | R7: =ROUND(R6*'Assumptions'!B8,0) | S7: =ROUND(S6*'Assumptions'!B8,0) | T7: =ROUND(T6*'Assumptions'!B8,0) | U7: =ROUND(U6*'Assumptions'!B8,0) | V7: =ROUND(V6*'Assumptions'!B8,0) | W7: =ROUND(W6*'Assumptions'!B8,0) | X7: =ROUND(X6*'Assumptions'!B8,0) | Y7: =ROUND(Y6*'Assumptions'!B8,0) | Z7: =ROUND(Z6*'Assumptions'!B8,0) | AA7: =ROUND(AA6*'Assumptions'!B8,0) | AB7: =ROUND(AB6*'Assumptions'!B8,0) | AC7: =ROUND(AC6*'Assumptions'!B8,0) | AD7: =ROUND(AD6*'Assumptions'!B8,0) | AE7: =ROUND(AE6*'Assumptions'!B8,0) | AF7: =ROUND(AF6*'Assumptions'!B8,0) | AG7: =ROUND(AG6*'Assumptions'!B8,0) | AH7: =ROUND(AH6*'Assumptions'!B8,0) | AI7: =ROUND(AI6*'Assumptions'!B8,0) | AJ7: =ROUND(AJ6*'Assumptions'!B8,0) | AK7: =ROUND(AK6*'Assumptions'!B8,0)
A8: Lead Credit Revenue PHP | B8: =ROUND(B3*'Assumptions'!B9,0) | C8: =ROUND(C3*'Assumptions'!B9,0) | D8: =ROUND(D3*'Assumptions'!B9,0) | E8: =ROUND(E3*'Assumptions'!B9,0) | F8: =ROUND(F3*'Assumptions'!B9,0) | G8: =ROUND(G3*'Assumptions'!B9,0) | H8: =ROUND(H3*'Assumptions'!B9,0) | I8: =ROUND(I3*'Assumptions'!B9,0) | J8: =ROUND(J3*'Assumptions'!B9,0) | K8: =ROUND(K3*'Assumptions'!B9,0) | L8: =ROUND(L3*'Assumptions'!B9,0) | M8: =ROUND(M3*'Assumptions'!B9,0) | N8: =ROUND(N3*'Assumptions'!B9,0) | O8: =ROUND(O3*'Assumptions'!B9,0) | P8: =ROUND(P3*'Assumptions'!B9,0) | Q8: =ROUND(Q3*'Assumptions'!B9,0) | R8: =ROUND(R3*'Assumptions'!B9,0) | S8: =ROUND(S3*'Assumptions'!B9,0) | T8: =ROUND(T3*'Assumptions'!B9,0) | U8: =ROUND(U3*'Assumptions'!B9,0) | V8: =ROUND(V3*'Assumptions'!B9,0) | W8: =ROUND(W3*'Assumptions'!B9,0) | X8: =ROUND(X3*'Assumptions'!B9,0) | Y8: =ROUND(Y3*'Assumptions'!B9,0) | Z8: =ROUND(Z3*'Assumptions'!B9,0) | AA8: =ROUND(AA3*'Assumptions'!B9,0) | AB8: =ROUND(AB3*'Assumptions'!B9,0) | AC8: =ROUND(AC3*'Assumptions'!B9,0) | AD8: =ROUND(AD3*'Assumptions'!B9,0) | AE8: =ROUND(AE3*'Assumptions'!B9,0) | AF8: =ROUND(AF3*'Assumptions'!B9,0) | AG8: =ROUND(AG3*'Assumptions'!B9,0) | AH8: =ROUND(AH3*'Assumptions'!B9,0) | AI8: =ROUND(AI3*'Assumptions'!B9,0) | AJ8: =ROUND(AJ3*'Assumptions'!B9,0) | AK8: =ROUND(AK3*'Assumptions'!B9,0)
A9: Premium Revenue PHP | B9: =ROUND(B3*'Assumptions'!B10*'Assumptions'!B11,0) | C9: =ROUND(C3*'Assumptions'!B10*'Assumptions'!B11,0) | D9: =ROUND(D3*'Assumptions'!B10*'Assumptions'!B11,0) | E9: =ROUND(E3*'Assumptions'!B10*'Assumptions'!B11,0) | F9: =ROUND(F3*'Assumptions'!B10*'Assumptions'!B11,0) | G9: =ROUND(G3*'Assumptions'!B10*'Assumptions'!B11,0) | H9: =ROUND(H3*'Assumptions'!B10*'Assumptions'!B11,0) | I9: =ROUND(I3*'Assumptions'!B10*'Assumptions'!B11,0) | J9: =ROUND(J3*'Assumptions'!B10*'Assumptions'!B11,0) | K9: =ROUND(K3*'Assumptions'!B10*'Assumptions'!B11,0) | L9: =ROUND(L3*'Assumptions'!B10*'Assumptions'!B11,0) | M9: =ROUND(M3*'Assumptions'!B10*'Assumptions'!B11,0) | N9: =ROUND(N3*'Assumptions'!B10*'Assumptions'!B11,0) | O9: =ROUND(O3*'Assumptions'!B10*'Assumptions'!B11,0) | P9: =ROUND(P3*'Assumptions'!B10*'Assumptions'!B11,0) | Q9: =ROUND(Q3*'Assumptions'!B10*'Assumptions'!B11,0) | R9: =ROUND(R3*'Assumptions'!B10*'Assumptions'!B11,0) | S9: =ROUND(S3*'Assumptions'!B10*'Assumptions'!B11,0) | T9: =ROUND(T3*'Assumptions'!B10*'Assumptions'!B11,0) | U9: =ROUND(U3*'Assumptions'!B10*'Assumptions'!B11,0) | V9: =ROUND(V3*'Assumptions'!B10*'Assumptions'!B11,0) | W9: =ROUND(W3*'Assumptions'!B10*'Assumptions'!B11,0) | X9: =ROUND(X3*'Assumptions'!B10*'Assumptions'!B11,0) | Y9: =ROUND(Y3*'Assumptions'!B10*'Assumptions'!B11,0) | Z9: =ROUND(Z3*'Assumptions'!B10*'Assumptions'!B11,0) | AA9: =ROUND(AA3*'Assumptions'!B10*'Assumptions'!B11,0) | AB9: =ROUND(AB3*'Assumptions'!B10*'Assumptions'!B11,0) | AC9: =ROUND(AC3*'Assumptions'!B10*'Assumptions'!B11,0) | AD9: =ROUND(AD3*'Assumptions'!B10*'Assumptions'!B11,0) | AE9: =ROUND(AE3*'Assumptions'!B10*'Assumptions'!B11,0) | AF9: =ROUND(AF3*'Assumptions'!B10*'Assumptions'!B11,0) | AG9: =ROUND(AG3*'Assumptions'!B10*'Assumptions'!B11,0) | AH9: =ROUND(AH3*'Assumptions'!B10*'Assumptions'!B11,0) | AI9: =ROUND(AI3*'Assumptions'!B10*'Assumptions'!B11,0) | AJ9: =ROUND(AJ3*'Assumptions'!B10*'Assumptions'!B11,0) | AK9: =ROUND(AK3*'Assumptions'!B10*'Assumptions'!B11,0)
A10: Total Revenue PHP | B10: =ROUND(SUM(B7:B9),0) | C10: =ROUND(SUM(C7:C9),0) | D10: =ROUND(SUM(D7:D9),0) | E10: =ROUND(SUM(E7:E9),0) | F10: =ROUND(SUM(F7:F9),0) | G10: =ROUND(SUM(G7:G9),0) | H10: =ROUND(SUM(H7:H9),0) | I10: =ROUND(SUM(I7:I9),0) | ... AK10: =ROUND(SUM(AK7:AK9),0)
A11: Hosting/Tools PHP | B11: =ROUND('Assumptions'!B12,0) | C11: =ROUND('Assumptions'!B12,0) | D11: =ROUND('Assumptions'!B12,0) | E11: =ROUND('Assumptions'!B12,0) | F11: =ROUND('Assumptions'!B12,0) | G11: =ROUND('Assumptions'!B12,0) | H11: =ROUND('Assumptions'!B12,0) | I11: =ROUND('Assumptions'!B12,0) | J11: =ROUND('Assumptions'!B12,0) | K11: =ROUND('Assumptions'!B12,0) | L11: =ROUND('Assumptions'!B12,0) | M11: =ROUND('Assumptions'!B12,0) | N11: =ROUND('Assumptions'!B12,0) | O11: =ROUND('Assumptions'!B12,0) | P11: =ROUND('Assumptions'!B12,0) | Q11: =ROUND('Assumptions'!B12,0) | R11: =ROUND('Assumptions'!B12,0) | S11: =ROUND('Assumptions'!B12,0) | T11: =ROUND('Assumptions'!B12,0) | U11: =ROUND('Assumptions'!B12,0) | V11: =ROUND('Assumptions'!B12,0) | W11: =ROUND('Assumptions'!B12,0) | X11: =ROUND('Assumptions'!B12,0) | Y11: =ROUND('Assumptions'!B12,0) | Z11: =ROUND('Assumptions'!B12,0) | AA11: =ROUND('Assumptions'!B12,0) | AB11: =ROUND('Assumptions'!B12,0) | AC11: =ROUND('Assumptions'!B12,0) | AD11: =ROUND('Assumptions'!B12,0) | AE11: =ROUND('Assumptions'!B12,0) | AF11: =ROUND('Assumptions'!B12,0) | AG11: =ROUND('Assumptions'!B12,0) | AH11: =ROUND('Assumptions'!B12,0) | AI11: =ROUND('Assumptions'!B12,0) | AJ11: =ROUND('Assumptions'!B12,0) | AK11: =ROUND('Assumptions'!B12,0)
A12: Marketing PHP | B12: =ROUND('Assumptions'!B13,0) | C12: =ROUND('Assumptions'!B13,0) | D12: =ROUND('Assumptions'!B13,0) | E12: =ROUND('Assumptions'!B13,0) | F12: =ROUND('Assumptions'!B13,0) | G12: =ROUND('Assumptions'!B13,0) | H12: =ROUND('Assumptions'!B13,0) | I12: =ROUND('Assumptions'!B13,0) | J12: =ROUND('Assumptions'!B13,0) | K12: =ROUND('Assumptions'!B13,0) | L12: =ROUND('Assumptions'!B13,0) | M12: =ROUND('Assumptions'!B13,0) | N12: =ROUND('Assumptions'!B13,0) | O12: =ROUND('Assumptions'!B13,0) | P12: =ROUND('Assumptions'!B13,0) | Q12: =ROUND('Assumptions'!B13,0) | R12: =ROUND('Assumptions'!B13,0) | S12: =ROUND('Assumptions'!B13,0) | T12: =ROUND('Assumptions'!B13,0) | U12: =ROUND('Assumptions'!B13,0) | V12: =ROUND('Assumptions'!B13,0) | W12: =ROUND('Assumptions'!B13,0) | X12: =ROUND('Assumptions'!B13,0) | Y12: =ROUND('Assumptions'!B13,0) | Z12: =ROUND('Assumptions'!B13,0) | AA12: =ROUND('Assumptions'!B13,0) | AB12: =ROUND('Assumptions'!B13,0) | AC12: =ROUND('Assumptions'!B13,0) | AD12: =ROUND('Assumptions'!B13,0) | AE12: =ROUND('Assumptions'!B13,0) | AF12: =ROUND('Assumptions'!B13,0) | AG12: =ROUND('Assumptions'!B13,0) | AH12: =ROUND('Assumptions'!B13,0) | AI12: =ROUND('Assumptions'!B13,0) | AJ12: =ROUND('Assumptions'!B13,0) | AK12: =ROUND('Assumptions'!B13,0)
A13: Operations Support PHP | B13: =ROUND('Assumptions'!B14,0) | C13: =ROUND('Assumptions'!B14,0) | D13: =ROUND('Assumptions'!B14,0) | E13: =ROUND('Assumptions'!B14,0) | F13: =ROUND('Assumptions'!B14,0) | G13: =ROUND('Assumptions'!B14,0) | H13: =ROUND('Assumptions'!B14,0) | I13: =ROUND('Assumptions'!B14,0) | J13: =ROUND('Assumptions'!B14,0) | K13: =ROUND('Assumptions'!B14,0) | L13: =ROUND('Assumptions'!B14,0) | M13: =ROUND('Assumptions'!B14,0) | N13: =ROUND('Assumptions'!B14,0) | O13: =ROUND('Assumptions'!B14,0) | P13: =ROUND('Assumptions'!B14,0) | Q13: =ROUND('Assumptions'!B14,0) | R13: =ROUND('Assumptions'!B14,0) | S13: =ROUND('Assumptions'!B14,0) | T13: =ROUND('Assumptions'!B14,0) | U13: =ROUND('Assumptions'!B14,0) | V13: =ROUND('Assumptions'!B14,0) | W13: =ROUND('Assumptions'!B14,0) | X13: =ROUND('Assumptions'!B14,0) | Y13: =ROUND('Assumptions'!B14,0) | Z13: =ROUND('Assumptions'!B14,0) | AA13: =ROUND('Assumptions'!B14,0) | AB13: =ROUND('Assumptions'!B14,0) | AC13: =ROUND('Assumptions'!B14,0) | AD13: =ROUND('Assumptions'!B14,0) | AE13: =ROUND('Assumptions'!B14,0) | AF13: =ROUND('Assumptions'!B14,0) | AG13: =ROUND('Assumptions'!B14,0) | AH13: =ROUND('Assumptions'!B14,0) | AI13: =ROUND('Assumptions'!B14,0) | AJ13: =ROUND('Assumptions'!B14,0) | AK13: =ROUND('Assumptions'!B14,0)
A14: Legal/Admin PHP | B14: =ROUND('Assumptions'!B15,0) | C14: =ROUND('Assumptions'!B15,0) | D14: =ROUND('Assumptions'!B15,0) | E14: =ROUND('Assumptions'!B15,0) | F14: =ROUND('Assumptions'!B15,0) | G14: =ROUND('Assumptions'!B15,0) | H14: =ROUND('Assumptions'!B15,0) | I14: =ROUND('Assumptions'!B15,0) | J14: =ROUND('Assumptions'!B15,0) | K14: =ROUND('Assumptions'!B15,0) | L14: =ROUND('Assumptions'!B15,0) | M14: =ROUND('Assumptions'!B15,0) | N14: =ROUND('Assumptions'!B15,0) | O14: =ROUND('Assumptions'!B15,0) | P14: =ROUND('Assumptions'!B15,0) | Q14: =ROUND('Assumptions'!B15,0) | R14: =ROUND('Assumptions'!B15,0) | S14: =ROUND('Assumptions'!B15,0) | T14: =ROUND('Assumptions'!B15,0) | U14: =ROUND('Assumptions'!B15,0) | V14: =ROUND('Assumptions'!B15,0) | W14: =ROUND('Assumptions'!B15,0) | X14: =ROUND('Assumptions'!B15,0) | Y14: =ROUND('Assumptions'!B15,0) | Z14: =ROUND('Assumptions'!B15,0) | AA14: =ROUND('Assumptions'!B15,0) | AB14: =ROUND('Assumptions'!B15,0) | AC14: =ROUND('Assumptions'!B15,0) | AD14: =ROUND('Assumptions'!B15,0) | AE14: =ROUND('Assumptions'!B15,0) | AF14: =ROUND('Assumptions'!B15,0) | AG14: =ROUND('Assumptions'!B15,0) | AH14: =ROUND('Assumptions'!B15,0) | AI14: =ROUND('Assumptions'!B15,0) | AJ14: =ROUND('Assumptions'!B15,0) | AK14: =ROUND('Assumptions'!B15,0)
A15: SMS/Notification PHP | B15: =ROUND(B4*'Assumptions'!B16,0) | C15: =ROUND(C4*'Assumptions'!B16,0) | D15: =ROUND(D4*'Assumptions'!B16,0) | E15: =ROUND(E4*'Assumptions'!B16,0) | F15: =ROUND(F4*'Assumptions'!B16,0) | G15: =ROUND(G4*'Assumptions'!B16,0) | H15: =ROUND(H4*'Assumptions'!B16,0) | I15: =ROUND(I4*'Assumptions'!B16,0) | J15: =ROUND(J4*'Assumptions'!B16,0) | K15: =ROUND(K4*'Assumptions'!B16,0) | L15: =ROUND(L4*'Assumptions'!B16,0) | M15: =ROUND(M4*'Assumptions'!B16,0) | N15: =ROUND(N4*'Assumptions'!B16,0) | O15: =ROUND(O4*'Assumptions'!B16,0) | P15: =ROUND(P4*'Assumptions'!B16,0) | Q15: =ROUND(Q4*'Assumptions'!B16,0) | R15: =ROUND(R4*'Assumptions'!B16,0) | S15: =ROUND(S4*'Assumptions'!B16,0) | T15: =ROUND(T4*'Assumptions'!B16,0) | U15: =ROUND(U4*'Assumptions'!B16,0) | V15: =ROUND(V4*'Assumptions'!B16,0) | W15: =ROUND(W4*'Assumptions'!B16,0) | X15: =ROUND(X4*'Assumptions'!B16,0) | Y15: =ROUND(Y4*'Assumptions'!B16,0) | Z15: =ROUND(Z4*'Assumptions'!B16,0) | AA15: =ROUND(AA4*'Assumptions'!B16,0) | AB15: =ROUND(AB4*'Assumptions'!B16,0) | AC15: =ROUND(AC4*'Assumptions'!B16,0) | AD15: =ROUND(AD4*'Assumptions'!B16,0) | AE15: =ROUND(AE4*'Assumptions'!B16,0) | AF15: =ROUND(AF4*'Assumptions'!B16,0) | AG15: =ROUND(AG4*'Assumptions'!B16,0) | AH15: =ROUND(AH4*'Assumptions'!B16,0) | AI15: =ROUND(AI4*'Assumptions'!B16,0) | AJ15: =ROUND(AJ4*'Assumptions'!B16,0) | AK15: =ROUND(AK4*'Assumptions'!B16,0)
A16: Development PHP | B16: =ROUND('Assumptions'!B17,0) | C16: =ROUND('Assumptions'!B17,0) | D16: =ROUND('Assumptions'!B17,0) | E16: =ROUND('Assumptions'!B17,0) | F16: =ROUND('Assumptions'!B17,0) | G16: =ROUND('Assumptions'!B17,0) | H16: =ROUND('Assumptions'!B17,0) | I16: =ROUND('Assumptions'!B17,0) | J16: =ROUND('Assumptions'!B17,0) | K16: =ROUND('Assumptions'!B17,0) | L16: =ROUND('Assumptions'!B17,0) | M16: =ROUND('Assumptions'!B17,0) | N16: =ROUND('Assumptions'!B17,0) | O16: =ROUND('Assumptions'!B17,0) | P16: =ROUND('Assumptions'!B17,0) | Q16: =ROUND('Assumptions'!B17,0) | R16: =ROUND('Assumptions'!B17,0) | S16: =ROUND('Assumptions'!B17,0) | T16: =ROUND('Assumptions'!B17,0) | U16: =ROUND('Assumptions'!B17,0) | V16: =ROUND('Assumptions'!B17,0) | W16: =ROUND('Assumptions'!B17,0) | X16: =ROUND('Assumptions'!B17,0) | Y16: =ROUND('Assumptions'!B17,0) | Z16: =ROUND('Assumptions'!B17,0) | AA16: =ROUND('Assumptions'!B17,0) | AB16: =ROUND('Assumptions'!B17,0) | AC16: =ROUND('Assumptions'!B17,0) | AD16: =ROUND('Assumptions'!B17,0) | AE16: =ROUND('Assumptions'!B17,0) | AF16: =ROUND('Assumptions'!B17,0) | AG16: =ROUND('Assumptions'!B17,0) | AH16: =ROUND('Assumptions'!B17,0) | AI16: =ROUND('Assumptions'!B17,0) | AJ16: =ROUND('Assumptions'!B17,0) | AK16: =ROUND('Assumptions'!B17,0)
A17: Total Expenses PHP | B17: =ROUND(SUM(B11:B16),0) | C17: =ROUND(SUM(C11:C16),0) | D17: =ROUND(SUM(D11:D16),0) | E17: =ROUND(SUM(E11:E16),0) | F17: =ROUND(SUM(F11:F16),0) | G17: =ROUND(SUM(G11:G16),0) | H17: =ROUND(SUM(H11:H16),0) | I17: =ROUND(SUM(I11:I16),0) | ... AK17: =ROUND(SUM(AK11:AK16),0)
A18: Net Cash Flow PHP | B18: =ROUND(B10-B17,0) | C18: =ROUND(C10-C17,0) | D18: =ROUND(D10-D17,0) | E18: =ROUND(E10-E17,0) | F18: =ROUND(F10-F17,0) | G18: =ROUND(G10-G17,0) | H18: =ROUND(H10-H17,0) | I18: =ROUND(I10-I17,0) | ... AK18: =ROUND(AK10-AK17,0)
A19: Cumulative Cash PHP | B19: =ROUND(B18,0) | C19: =ROUND(B19+C18,0) | D19: =ROUND(C19+D18,0) | E19: =ROUND(D19+E18,0) | F19: =ROUND(E19+F18,0) | G19: =ROUND(F19+G18,0) | H19: =ROUND(G19+H18,0) | I19: =ROUND(H19+I18,0) | J19: =ROUND(I19+J18,0) | ... AK19: =ROUND(AJ19+AK18,0)

Sheet Annual Summary
A1: Annual Summary
A2: Metric | B2: Year 1 | C2: Year 2 | D2: Year 3
A3: Posted Requests | B3: =ROUND(SUM('Monthly Projection'!B4:M4),0) | C3: =ROUND(SUM('Monthly Projection'!N4:Y4),0) | D3: =ROUND(SUM('Monthly Projection'!Z4:AK4),0)
A4: Completed Jobs | B4: =ROUND(SUM('Monthly Projection'!B5:M5),0) | C4: =ROUND(SUM('Monthly Projection'!N5:Y5),0) | D4: =ROUND(SUM('Monthly Projection'!Z5:AK5),0)
A5: GMV PHP | B5: =ROUND(SUM('Monthly Projection'!B6:M6),0) | C5: =ROUND(SUM('Monthly Projection'!N6:Y6),0) | D5: =ROUND(SUM('Monthly Projection'!Z6:AK6),0)
A6: Total Revenue PHP | B6: =ROUND(SUM('Monthly Projection'!B10:M10),0) | C6: =ROUND(SUM('Monthly Projection'!N10:Y10),0) | D6: =ROUND(SUM('Monthly Projection'!Z10:AK10),0)
A7: Total Expenses PHP | B7: =ROUND(SUM('Monthly Projection'!B17:M17),0) | C7: =ROUND(SUM('Monthly Projection'!N17:Y17),0) | D7: =ROUND(SUM('Monthly Projection'!Z17:AK17),0)
A8: Net Cash Flow PHP | B8: =ROUND(SUM('Monthly Projection'!B18:M18),0) | C8: =ROUND(SUM('Monthly Projection'!N18:Y18),0) | D8: =ROUND(SUM('Monthly Projection'!Z18:AK18),0)
A9: Ending Cumulative Cash PHP | B9: =ROUND('Monthly Projection'!M19,0) | C9: =ROUND('Monthly Projection'!Y19,0) | D9: =ROUND('Monthly Projection'!AK19,0)

Sheet Unit Economics
A1: Unit Economics
A2: Metric | B2: Value | C2: Notes
A3: Average Job Value PHP | B3: ='Assumptions'!B7 | C3: Editable in Assumptions
A4: Take Rate | B4: ='Assumptions'!B8 | C4: Commission percentage if enabled
A5: Revenue per Completed Job PHP | B5: ='Assumptions'!B7*'Assumptions'!B8 | C5: Commission revenue only
A6: Notification Cost per Posted Request PHP | B6: ='Assumptions'!B16 | C6: Set to 0 if using free channels
A7: Estimated Completion Rate | B7: ='Assumptions'!B6 | C7: Completed jobs divided by posted requests
A8: Notification Cost per Completed Job PHP | B8: =IF(B7>0,B6/B7,0) | C8: Cost allocation
A9: Gross Contribution per Completed Job PHP | B9: =B5-B8 | C9: Before fixed costs
A10: Break-even Completed Jobs per Month | B10: =IF(B9>0,('Assumptions'!B12+'Assumptions'!B13+'Assumptions'!B14+'Assumptions'!B15+'Assumptions'!B17)/B9, "N/A") | C10: Only meaningful when monetization is active
